jaxpm/__init__.py
jaxpm/_version.py
jaxpm/distributed.py
jaxpm/growth.py
jaxpm/kernels.py
jaxpm/lensing.py
jaxpm/nn.py
jaxpm/painting.py
jaxpm/painting_utils.py
jaxpm/plotting.py
jaxpm/pm.py
jaxpm/utils.py
jaxpm-0.1.6.dist-info/licenses/LICENSE
jaxpm-0.1.6.dist-info/METADATA
jaxpm-0.1.6.dist-info/WHEEL
jaxpm-0.1.6.dist-info/top_level.txt
jaxpm-0.1.6.dist-info/RECORD
