Metadata-Version: 2.4
Name: jaxpm
Version: 0.1.6
Summary: A simple Particle-Mesh implementation in JAX
Author: JaxPM developers
License: MIT License
Project-URL: Homepage, https://github.com/DifferentiableUniverseInitiative/JaxPM
Requires-Python: >=3.9
License-File: LICENSE
Requires-Dist: jax_cosmo
Requires-Dist: jax>=0.4.35
Requires-Dist: jaxdecomp>=0.2.3
Dynamic: license-file
